LICENSE
MANIFEST.in
README.md
requirements.txt
setup.py
xleditor.py
xleditor.egg-info/PKG-INFO
xleditor.egg-info/SOURCES.txt
xleditor.egg-info/dependency_links.txt
xleditor.egg-info/requires.txt
xleditor.egg-info/top_level.txt