Metadata-Version: 1.1
Name: xleditor
Version: 0.95
Summary: Easy to open xls/xlsx file and edit it (merge xlrd and xlutils)
Home-page: https://github.com/taojy123/xleditor
Author: TaoJY
Author-email: taojy123@163.com
License: MIT License
Platform: all
Classifier: Programming Language :: Python
Classifier: Programming Language :: Python :: Implementation
Classifier: Programming Language :: Python :: 2
Classifier: Programming Language :: Python :: 2.7
Classifier: Programming Language :: Python :: 3
Classifier: Programming Language :: Python :: 3.4
Classifier: Programming Language :: Python :: 3.5
Classifier: Programming Language :: Python :: 3.6
Classifier: Topic :: Software Development :: Libraries
